{
    "undergradTotal": [
        {
            "college": "KL",
            "name": "Agr, Cons, Env Sci",
            "level": "Undergraduate",
            "total": 2253,
            "year": 2004,
            "Caucasian": 1908,
            "Asian American": 122,
            "African American": 79,
            "Hispanic": 71,
            "Native American": 1,
            "Hawaiian/ Pacific Isl": 35,
            "Multiracial": 37,
            "International": 2167,
            "Unknown": 86
        },
        {
            "college": "KM",
            "name": "Business",
            "level": "Undergraduate",
            "total": 2933,
            "year": 2004,
            "Caucasian": 1919,
            "Asian American": 461,
            "African American": 114,
            "Hispanic": 163,
            "Native American": 5,
            "Hawaiian/ Pacific Isl": 234,
            "Multiracial": 37,
            "International": 2504,
            "Unknown": 429
        },
        {
            "college": "KN",
            "name": "Education",
            "level": "Undergraduate",
            "total": 724,
            "year": 2004,
            "Caucasian": 592,
            "Asian American": 57,
            "African American": 33,
            "Hispanic": 33,
            "Native American": 2,
            "Hawaiian/ Pacific Isl": 2,
            "Multiracial": 5,
            "International": 708,
            "Unknown": 16
        },
        {
            "college": "KP",
            "name": "Engineering",
            "level": "Undergraduate",
            "total": 5116,
            "year": 2004,
            "Caucasian": 3296,
            "Asian American": 1009,
            "African American": 94,
            "Hispanic": 198,
            "Native American": 8,
            "Hawaiian/ Pacific Isl": 418,
            "Multiracial": 93,
            "International": 3900,
            "Unknown": 1216
        },
        {
            "college": "KR",
            "name": "Fine & Applied Arts",
            "level": "Undergraduate",
            "total": 1899,
            "year": 2004,
            "Caucasian": 1443,
            "Asian American": 162,
            "African American": 79,
            "Hispanic": 85,
            "Native American": 3,
            "Hawaiian/ Pacific Isl": 83,
            "Multiracial": 44,
            "International": 1654,
            "Unknown": 245
        },
        {
            "college": "KT",
            "name": "Communications",
            "level": "Undergraduate",
            "total": 541,
            "year": 2004,
            "Caucasian": 393,
            "Asian American": 54,
            "African American": 44,
            "Hispanic": 35,
            "Native American": 0,
            "Hawaiian/ Pacific Isl": 7,
            "Multiracial": 8,
            "International": 502,
            "Unknown": 39
        },
        {
            "college": "KV",
            "name": "Liberal Arts & Sci",
            "level": "Undergraduate",
            "total": 14092,
            "year": 2004,
            "Caucasian": 8967,
            "Asian American": 1825,
            "African American": 1348,
            "Hispanic": 1179,
            "Native American": 49,
            "Hawaiian/ Pacific Isl": 490,
            "Multiracial": 234,
            "International": 12879,
            "Unknown": 1213
        },
        {
            "college": "KY",
            "name": "Applied Life Studies",
            "level": "Undergraduate",
            "total": 1467,
            "year": 2004,
            "Caucasian": 1104,
            "Asian American": 60,
            "African American": 192,
            "Hispanic": 82,
            "Native American": 5,
            "Hawaiian/ Pacific Isl": 15,
            "Multiracial": 9,
            "International": 1369,
            "Unknown": 98
        },
        {
            "college": "LE",
            "name": "Institute of Aviation",
            "level": "Undergraduate",
            "total": 255,
            "year": 2004,
            "Caucasian": 217,
            "Asian American": 12,
            "African American": 7,
            "Hispanic": 12,
            "Native American": 0,
            "Hawaiian/ Pacific Isl": 3,
            "Multiracial": 4,
            "International": 234,
            "Unknown": 21
        },
        {
            "college": "LN",
            "name": "Continuing Education",
            "level": "Undergraduate",
            "total": 4,
            "year": 2004,
            "Caucasian": 2,
            "Asian American": 0,
            "African American": 1,
            "Hispanic": 1,
            "Native American": 0,
            "Hawaiian/ Pacific Isl": 0,
            "Multiracial": 0,
            "International": 4,
            "Unknown": 0
        }
    ],
    "gradTotal": [
        {
            "college": "KL",
            "name": "Agr, Cons, Env Sci",
            "level": "Graduate",
            "total": 510,
            "year": 2004,
            "Caucasian": 279,
            "Asian American": 25,
            "African American": 9,
            "Hispanic": 12,
            "Native American": 0,
            "Hawaiian/ Pacific Isl": 181,
            "Multiracial": 4,
            "International": 216,
            "Unknown": 294
        },
        {
            "college": "KM",
            "name": "Business",
            "level": "Graduate",
            "total": 775,
            "year": 2004,
            "Caucasian": 272,
            "Asian American": 83,
            "African American": 14,
            "Hispanic": 7,
            "Native American": 1,
            "Hawaiian/ Pacific Isl": 364,
            "Multiracial": 34,
            "International": 313,
            "Unknown": 462
        },
        {
            "college": "KN",
            "name": "Education",
            "level": "Graduate",
            "total": 818,
            "year": 2004,
            "Caucasian": 388,
            "Asian American": 30,
            "African American": 107,
            "Hispanic": 51,
            "Native American": 5,
            "Hawaiian/ Pacific Isl": 214,
            "Multiracial": 23,
            "International": 490,
            "Unknown": 328
        },
        {
            "college": "KP",
            "name": "Engineering",
            "level": "Graduate",
            "total": 2472,
            "year": 2004,
            "Caucasian": 905,
            "Asian American": 211,
            "African American": 32,
            "Hispanic": 50,
            "Native American": 2,
            "Hawaiian/ Pacific Isl": 1248,
            "Multiracial": 24,
            "International": 493,
            "Unknown": 1979
        },
        {
            "college": "KR",
            "name": "Fine & Applied Arts",
            "level": "Graduate",
            "total": 793,
            "year": 2004,
            "Caucasian": 483,
            "Asian American": 43,
            "African American": 23,
            "Hispanic": 29,
            "Native American": 4,
            "Hawaiian/ Pacific Isl": 196,
            "Multiracial": 15,
            "International": 315,
            "Unknown": 478
        },
        {
            "college": "KS",
            "name": "Graduate College",
            "level": "Graduate",
            "total": 3,
            "year": 2004,
            "Caucasian": 2,
            "Asian American": 0,
            "African American": 0,
            "Hispanic": 0,
            "Native American": 1,
            "Hawaiian/ Pacific Isl": 0,
            "Multiracial": 0,
            "International": 3,
            "Unknown": 0
        },
        {
            "college": "KT",
            "name": "Communications",
            "level": "Graduate",
            "total": 108,
            "year": 2004,
            "Caucasian": 60,
            "Asian American": 4,
            "African American": 5,
            "Hispanic": 7,
            "Native American": 0,
            "Hawaiian/ Pacific Isl": 30,
            "Multiracial": 2,
            "International": 35,
            "Unknown": 73
        },
        {
            "college": "KU",
            "name": "Law",
            "level": "Graduate",
            "total": 37,
            "year": 2004,
            "Caucasian": 2,
            "Asian American": 1,
            "African American": 0,
            "Hispanic": 0,
            "Native American": 0,
            "Hawaiian/ Pacific Isl": 34,
            "Multiracial": 0,
            "International": 5,
            "Unknown": 32
        },
        {
            "college": "KU",
            "name": "Law",
            "level": "Professional",
            "total": 671,
            "year": 2004,
            "Caucasian": 399,
            "Asian American": 110,
            "African American": 51,
            "Hispanic": 50,
            "Native American": 4,
            "Hawaiian/ Pacific Isl": 13,
            "Multiracial": 44,
            "International": 503,
            "Unknown": 168
        },
        {
            "college": "KV",
            "name": "Liberal Arts & Sci",
            "level": "Graduate",
            "total": 2580,
            "year": 2004,
            "Caucasian": 1228,
            "Asian American": 154,
            "African American": 56,
            "Hispanic": 87,
            "Native American": 5,
            "Hawaiian/ Pacific Isl": 1027,
            "Multiracial": 23,
            "International": 487,
            "Unknown": 2093
        },
        {
            "college": "KY",
            "name": "Applied Life Studies",
            "level": "Graduate",
            "total": 214,
            "year": 2004,
            "Caucasian": 130,
            "Asian American": 13,
            "African American": 19,
            "Hispanic": 6,
            "Native American": 0,
            "Hawaiian/ Pacific Isl": 45,
            "Multiracial": 1,
            "International": 115,
            "Unknown": 99
        },
        {
            "college": "LC",
            "name": "Veterinary Medicine",
            "level": "Graduate",
            "total": 72,
            "year": 2004,
            "Caucasian": 31,
            "Asian American": 1,
            "African American": 3,
            "Hispanic": 4,
            "Native American": 0,
            "Hawaiian/ Pacific Isl": 33,
            "Multiracial": 0,
            "International": 16,
            "Unknown": 56
        },
        {
            "college": "LC",
            "name": "Veterinary Medicine",
            "level": "Professional",
            "total": 397,
            "year": 2004,
            "Caucasian": 337,
            "Asian American": 15,
            "African American": 2,
            "Hispanic": 6,
            "Native American": 0,
            "Hawaiian/ Pacific Isl": 2,
            "Multiracial": 35,
            "International": 346,
            "Unknown": 51
        },
        {
            "college": "LE",
            "name": "Institute of Aviation",
            "level": "Graduate",
            "total": 4,
            "year": 2004,
            "Caucasian": 2,
            "Asian American": 1,
            "African American": 0,
            "Hispanic": 0,
            "Native American": 0,
            "Hawaiian/ Pacific Isl": 1,
            "Multiracial": 0,
            "International": 2,
            "Unknown": 2
        },
        {
            "college": "LG",
            "name": "Labor & Industrial Relns",
            "level": "Graduate",
            "total": 149,
            "year": 2004,
            "Caucasian": 96,
            "Asian American": 8,
            "African American": 16,
            "Hispanic": 2,
            "Native American": 0,
            "Hawaiian/ Pacific Isl": 25,
            "Multiracial": 2,
            "International": 91,
            "Unknown": 58
        },
        {
            "college": "LL",
            "name": "School of Social Work",
            "level": "Graduate",
            "total": 297,
            "year": 2004,
            "Caucasian": 226,
            "Asian American": 3,
            "African American": 39,
            "Hispanic": 10,
            "Native American": 1,
            "Hawaiian/ Pacific Isl": 10,
            "Multiracial": 8,
            "International": 258,
            "Unknown": 39
        },
        {
            "college": "LN",
            "name": "Continuing Education",
            "level": "Graduate",
            "total": 65,
            "year": 2004,
            "Caucasian": 44,
            "Asian American": 9,
            "African American": 5,
            "Hispanic": 0,
            "Native American": 2,
            "Hawaiian/ Pacific Isl": 0,
            "Multiracial": 5,
            "International": 27,
            "Unknown": 38
        },
        {
            "college": "LP",
            "name": "Library & Info Sci",
            "level": "Graduate",
            "total": 267,
            "year": 2004,
            "Caucasian": 184,
            "Asian American": 14,
            "African American": 10,
            "Hispanic": 12,
            "Native American": 2,
            "Hawaiian/ Pacific Isl": 38,
            "Multiracial": 7,
            "International": 179,
            "Unknown": 88
        }
    ]
}